rfswarm_agent/__init__.py
rfswarm_agent/rfswarm_agent.py
rfswarm_agent/icons/rfswarm-agent-1024.png
rfswarm_agent/icons/rfswarm-agent-128.ico
rfswarm_agent/icons/rfswarm-agent-128.png
rfswarm_agent/icons/rfswarm-logo-128.ico
rfswarm_agent/icons/rfswarm-logo-128.png
rfswarm_agent-1.5.3.data/data/rfswarm_agent/icons/rfswarm-agent-1024.png
rfswarm_agent-1.5.3.data/data/rfswarm_agent/icons/rfswarm-agent-128.ico
rfswarm_agent-1.5.3.data/data/rfswarm_agent/icons/rfswarm-agent-128.png
rfswarm_agent-1.5.3.data/data/rfswarm_agent/icons/rfswarm-logo-128.ico
rfswarm_agent-1.5.3.data/data/rfswarm_agent/icons/rfswarm-logo-128.png
rfswarm_agent-1.5.3.dist-info/licenses/LICENSE
rfswarm_agent-1.5.3.dist-info/METADATA
rfswarm_agent-1.5.3.dist-info/WHEEL
rfswarm_agent-1.5.3.dist-info/entry_points.txt
rfswarm_agent-1.5.3.dist-info/top_level.txt
rfswarm_agent-1.5.3.dist-info/RECORD
