Metadata-Version: 2.4
Name: rfswarm-agent
Version: 1.5.3
Summary: rfswarm Agent
Home-page: https://github.com/damies13/rfswarm
Author: damies13
Author-email: damies13+rfswarm@gmail.com
Project-URL: Getting Help, https://github.com/damies13/rfswarm#getting-help
Project-URL: Say Thanks!, https://github.com/damies13/rfswarm#donations
Project-URL: Source, https://github.com/damies13/rfswarm
Classifier: Development Status :: 5 - Production/Stable
Classifier: Framework :: Robot Framework
Classifier: Framework :: Robot Framework :: Tool
Classifier: Topic :: Software Development :: Testing
Classifier: Programming Language :: Python :: 3.6
Classifier: License :: OSI Approved :: GNU General Public License v3 (GPLv3)
Classifier: Operating System :: OS Independent
Requires-Python: >=3.6
License-File: LICENSE
Requires-Dist: configparser
Requires-Dist: requests
Requires-Dist: robotframework
Requires-Dist: psutil
Requires-Dist: pyyaml
Dynamic: author
Dynamic: author-email
Dynamic: classifier
Dynamic: description
Dynamic: description-content-type
Dynamic: home-page
Dynamic: license-file
Dynamic: project-url
Dynamic: requires-dist
Dynamic: requires-python
Dynamic: summary
